Workbook

Sheet 1º Exemplo
A7: Data | B7: Vendedor | C7: ID_Prod | D7: Prod. | E7: Categoria | F7: Qtd. | G7: P.U | H7: P.T | I7: Desconto (4%) | J7: Total Líquido | K7: C.U | L7: Lucro Total | M7: Canal | N7: Cliente | O7: Forma_Pagamento
A8: =TODAY() -> 46178 | B8: Emanuel | C8: 222-Cab-109 | D8: =IF($C8="","",INDEX(Planilha2!B:B,MATCH('1º Exemplo'!C8,Planilha2!$A:$A,0))) -> Cabo HDMI 2 Metros | E8: =IF($C8="","",INDEX(Planilha2!E:E,MATCH('1º Exemplo'!$C8,Planilha2!$A:$A,0))) -> Cabos / Conetividade | F8: 2 | G8: 2000 | H8: =G8*F8 -> 4000
A9: =TODAY() -> 46178 | B9: Vanda | C9: 217-Pen-104 | D9: =IF($C9="","",INDEX(Planilha2!B:B,MATCH('1º Exemplo'!C9,Planilha2!$A:$A,0))) -> Pendrive 64GB Kingston | E9: =IF($C9="","",INDEX(Planilha2!E:E,MATCH('1º Exemplo'!$C9,Planilha2!$A:$A,0))) -> Armazenamento | F9: 3 | G9: 3000
A10: =TODAY() -> 46178 | B10: Aldina | C10: 220-Col-107 | D10: =IF($C10="","",INDEX(Planilha2!B:B,MATCH('1º Exemplo'!C10,Planilha2!$A:$A,0))) -> Coluna de Som Portátil | E10: =IF($C10="","",INDEX(Planilha2!E:E,MATCH('1º Exemplo'!$C10,Planilha2!$A:$A,0))) -> Áudio | F10: 4 | G10: 4000
A11: =TODAY() -> 46178 | B11: Fábio | C11: 224-Car-111 | D11: =IF($C11="","",INDEX(Planilha2!B:B,MATCH('1º Exemplo'!C11,Planilha2!$A:$A,0))) -> Carregador Universal Laptop | E11: =IF($C11="","",INDEX(Planilha2!E:E,MATCH('1º Exemplo'!$C11,Planilha2!$A:$A,0))) -> Energia | F11: 5 | G11: 5000
A12: =TODAY() -> 46178 | B12: Emanuel | C12: 215-Rat-102 | D12: =IF($C12="","",INDEX(Planilha2!B:B,MATCH('1º Exemplo'!C12,Planilha2!$A:$A,0))) -> Rato Sem Fios | E12: =IF($C12="","",INDEX(Planilha2!E:E,MATCH('1º Exemplo'!$C12,Planilha2!$A:$A,0))) -> Informática | F12: 10 | G12: 10000
A13: =TODAY() -> 46178 | B13: Emanuel | C13: 225-Pow-112 | D13: =IF($C13="","",INDEX(Planilha2!B:B,MATCH('1º Exemplo'!C13,Planilha2!$A:$A,0))) -> Powerbank 20.000mAh | E13: =IF($C13="","",INDEX(Planilha2!E:E,MATCH('1º Exemplo'!$C13,Planilha2!$A:$A,0))) -> Energia | F13: 11 | G13: 11000
A14: =TODAY() -> 46178 | B14: Emanuel | C14: 222-Cab-109 | D14: =IF($C14="","",INDEX(Planilha2!B:B,MATCH('1º Exemplo'!C14,Planilha2!$A:$A,0))) -> Cabo HDMI 2 Metros | E14: =IF($C14="","",INDEX(Planilha2!E:E,MATCH('1º Exemplo'!$C14,Planilha2!$A:$A,0))) -> Cabos / Conetividade | F14: 22 | G14: 6000
A15: =TODAY() -> 46178 | B15: Fábio | C15: 219-Aus-106 | D15: =IF($C15="","",INDEX(Planilha2!B:B,MATCH('1º Exemplo'!C15,Planilha2!$A:$A,0))) -> Auscultadores Bluetooth | E15: =IF($C15="","",INDEX(Planilha2!E:E,MATCH('1º Exemplo'!$C15,Planilha2!$A:$A,0))) -> Áudio | F15: 50 | G15: 5908
D16: =IF($C16="","",INDEX(Planilha2!B:B,MATCH('1º Exemplo'!C16,Planilha2!$A:$A,0))) | E16: =IF($C16="","",INDEX(Planilha2!E:E,MATCH('1º Exemplo'!$C16,Planilha2!$A:$A,0)))
D17: =IF($C17="","",INDEX(Planilha2!B:B,MATCH('1º Exemplo'!C17,Planilha2!$A:$A,0))) | E17: =IF($C17="","",INDEX(Planilha2!E:E,MATCH('1º Exemplo'!$C17,Planilha2!$A:$A,0)))
D18: =IF($C18="","",INDEX(Planilha2!B:B,MATCH('1º Exemplo'!C18,Planilha2!$A:$A,0))) | E18: =IF($C18="","",INDEX(Planilha2!E:E,MATCH('1º Exemplo'!$C18,Planilha2!$A:$A,0)))
D19: =IF($C19="","",INDEX(Planilha2!B:B,MATCH('1º Exemplo'!C19,Planilha2!$A:$A,0))) | E19: =IF($C19="","",INDEX(Planilha2!E:E,MATCH('1º Exemplo'!$C19,Planilha2!$A:$A,0)))
D20: =IF($C20="","",INDEX(Planilha2!B:B,MATCH('1º Exemplo'!C20,Planilha2!$A:$A,0))) | E20: =IF($C20="","",INDEX(Planilha2!E:E,MATCH('1º Exemplo'!$C20,Planilha2!$A:$A,0)))
D21: =IF($C21="","",INDEX(Planilha2!B:B,MATCH('1º Exemplo'!C21,Planilha2!$A:$A,0))) | E21: =IF($C21="","",INDEX(Planilha2!E:E,MATCH('1º Exemplo'!$C21,Planilha2!$A:$A,0)))
D22: =IF($C22="","",INDEX(Planilha2!B:B,MATCH('1º Exemplo'!C22,Planilha2!$A:$A,0))) | E22: =IF($C22="","",INDEX(Planilha2!E:E,MATCH('1º Exemplo'!$C22,Planilha2!$A:$A,0)))
D23: =IF($C23="","",INDEX(Planilha2!B:B,MATCH('1º Exemplo'!C23,Planilha2!$A:$A,0))) | E23: =IF($C23="","",INDEX(Planilha2!E:E,MATCH('1º Exemplo'!$C23,Planilha2!$A:$A,0)))
D24: =IF($C24="","",INDEX(Planilha2!B:B,MATCH('1º Exemplo'!C24,Planilha2!$A:$A,0))) | E24: =IF($C24="","",INDEX(Planilha2!E:E,MATCH('1º Exemplo'!$C24,Planilha2!$A:$A,0)))
D25: =IF($C25="","",INDEX(Planilha2!B:B,MATCH('1º Exemplo'!C25,Planilha2!$A:$A,0))) | E25: =IF($C25="","",INDEX(Planilha2!E:E,MATCH('1º Exemplo'!$C25,Planilha2!$A:$A,0)))
D26: =IF($C26="","",INDEX(Planilha2!B:B,MATCH('1º Exemplo'!C26,Planilha2!$A:$A,0))) | E26: =IF($C26="","",INDEX(Planilha2!E:E,MATCH('1º Exemplo'!$C26,Planilha2!$A:$A,0)))
D27: =IF($C27="","",INDEX(Planilha2!B:B,MATCH('1º Exemplo'!C27,Planilha2!$A:$A,0))) | E27: =IF($C27="","",INDEX(Planilha2!E:E,MATCH('1º Exemplo'!$C27,Planilha2!$A:$A,0)))
... D120: =IF($C120="","",INDEX(Planilha2!B:B,MATCH('1º Exemplo'!C120,Planilha2!$A:$A,0))) | E120: =IF($C120="","",INDEX(Planilha2!E:E,MATCH('1º Exemplo'!$C120,Planilha2!$A:$A,0)))

Sheet Planilha2
A1: ID | B1: Produto | C1: Custo | D1: P.U | E1: Categoria | F1: Esoque | G1: Em stoque
A2: =ROW($B2)+213 & "-" & LEFT($B2,3) & "-" & ROW($B2)+100 -> 215-Rat-102 | B2: Rato Sem Fios | C2: 5000 | D2: 9500 | E2: Informática | F2: 20 | G2: =Planilha2!F2-SUMIF('1º Exemplo'!C:C,Planilha2!A2,'1º Exemplo'!F:F) -> 10
A3: =ROW($B3)+213 & "-" & LEFT($B3,3) & "-" & ROW($B3)+100 -> 216-Tec-103 | B3: Teclado Mecânico RGB | C3: 12000 | D3: 22000 | E3: Informática | F3: 25 | G3: =Planilha2!F3-SUMIF('1º Exemplo'!C:C,Planilha2!A3,'1º Exemplo'!F:F) -> 25
A4: =ROW($B4)+213 & "-" & LEFT($B4,3) & "-" & ROW($B4)+100 -> 217-Pen-104 | B4: Pendrive 64GB Kingston | C4: 3500 | D4: 6500 | E4: Armazenamento | F4: 25 | G4: =Planilha2!F4-SUMIF('1º Exemplo'!C:C,Planilha2!A4,'1º Exemplo'!F:F) -> 22
A5: =ROW($B5)+213 & "-" & LEFT($B5,3) & "-" & ROW($B5)+100 -> 218-Dis-105 | B5: Disco Externo 1TB | C5: 25000 | D5: 42000 | E5: Armazenamento | F5: 18 | G5: =Planilha2!F5-SUMIF('1º Exemplo'!C:C,Planilha2!A5,'1º Exemplo'!F:F) -> 18
A6: =ROW($B6)+213 & "-" & LEFT($B6,3) & "-" & ROW($B6)+100 -> 219-Aus-106 | B6: Auscultadores Bluetooth | C6: 8000 | D6: 15000 | E6: Áudio | F6: 18 | G6: =Planilha2!F6-SUMIF('1º Exemplo'!C:C,Planilha2!A6,'1º Exemplo'!F:F) -> -32
A7: =ROW($B7)+213 & "-" & LEFT($B7,3) & "-" & ROW($B7)+100 -> 220-Col-107 | B7: Coluna de Som Portátil | C7: 14000 | D7: 26000 | E7: Áudio | F7: 25 | G7: =Planilha2!F7-SUMIF('1º Exemplo'!C:C,Planilha2!A7,'1º Exemplo'!F:F) -> 21
A8: =ROW($B8)+213 & "-" & LEFT($B8,3) & "-" & ROW($B8)+100 -> 221-Tap-108 | B8: Tapete de Rato Gaming (Grande) | C8: 3000 | D8: 6000 | E8: Acessórios | F8: 26 | G8: =Planilha2!F8-SUMIF('1º Exemplo'!C:C,Planilha2!A8,'1º Exemplo'!F:F) -> 26
A9: =ROW($B9)+213 & "-" & LEFT($B9,3) & "-" & ROW($B9)+100 -> 222-Cab-109 | B9: Cabo HDMI 2 Metros | C9: 2000 | D9: 4500 | E9: Cabos / Conetividade | F9: 12 | G9: =Planilha2!F9-SUMIF('1º Exemplo'!C:C,Planilha2!A9,'1º Exemplo'!F:F) -> -12
A10: =ROW($B10)+213 & "-" & LEFT($B10,3) & "-" & ROW($B10)+100 -> 223-Ada-110 | B10: Adaptador USB-C para HDMI | C10: 4500 | D10: 9000 | E10: Cabos / Conetividade | F10: 25 | G10: =Planilha2!F10-SUMIF('1º Exemplo'!C:C,Planilha2!A10,'1º Exemplo'!F:F) -> 25
A11: =ROW($B11)+213 & "-" & LEFT($B11,3) & "-" & ROW($B11)+100 -> 224-Car-111 | B11: Carregador Universal Laptop | C11: 9000 | D11: 17500 | E11: Energia | F11: 20 | G11: =Planilha2!F11-SUMIF('1º Exemplo'!C:C,Planilha2!A11,'1º Exemplo'!F:F) -> 15
A12: =ROW($B12)+213 & "-" & LEFT($B12,3) & "-" & ROW($B12)+100 -> 225-Pow-112 | B12: Powerbank 20.000mAh | C12: 11000 | D12: 20000 | E12: Energia | F12: 25 | G12: =Planilha2!F12-SUMIF('1º Exemplo'!C:C,Planilha2!A12,'1º Exemplo'!F:F) -> 14
A13: =ROW($B13)+213 & "-" & LEFT($B13,3) & "-" & ROW($B13)+100 -> 226-Res-113 | B13: Resma de Papel A4 (Chamex) | C13: 4500 | D13: 6500 | E13: Papelaria | F13: 24 | G13: =Planilha2!F13-SUMIF('1º Exemplo'!C:C,Planilha2!A13,'1º Exemplo'!F:F) -> 24
... A23: =ROW($B23)+213 & "-" & LEFT($B23,3) & "-" & ROW($B23)+100 -> 236-Mas-123 | B23: Massa Térmica Arctic MX-4 | C23: 4000 | D23: 8500 | E23: Manutenção | F23: 17 | G23: =Planilha2!F23-SUMIF('1º Exemplo'!C:C,Planilha2!A23,'1º Exemplo'!F:F) -> 17
